fisher_rxc-0.16.0.dist-info/METADATA
fisher_rxc-0.16.0.dist-info/WHEEL
fisher_rxc-0.16.0.dist-info/licenses/LICENSE
fisher/__init__.py
fisher/fisher.cp312-win32.pyd
fisher_rxc-0.16.0.dist-info/RECORD
