Metadata-Version: 2.4
Name: fisher-rxc
Version: 0.16.0
Classifier: Programming Language :: Rust
Classifier: Programming Language :: C
Classifier: Programming Language :: Python :: Implementation :: CPython
Classifier: Programming Language :: Python :: Implementation :: PyPy
Classifier: License :: OSI Approved :: MIT License
Classifier: Intended Audience :: Science/Research
Classifier: Topic :: Scientific/Engineering :: Mathematics
License-File: LICENSE
Summary: Fast multithreaded implementation for calculating Fisher's exact test for any RxC sized table
Requires-Python: >=3.9
Project-URL: Homepage, https://github.com/SakiiCode/fisher
Project-URL: Issues, https://github.com/SakiiCode/fisher/issues
